watchmen_storage_oracle/__init__.py
watchmen_storage_oracle/data_source_oracle.py
watchmen_storage_oracle/script_builder_oracle.py
watchmen_storage_oracle/storage_oracle.py
watchmen_storage_oracle/storage_oracle_configuration.py
watchmen_storage_oracle/table_creator.py
watchmen_storage_oracle/where_build.py
watchmen_storage_oracle-18.0.1.dist-info/METADATA
watchmen_storage_oracle-18.0.1.dist-info/WHEEL
watchmen_storage_oracle-18.0.1.dist-info/licenses/LICENSE
watchmen_storage_oracle-18.0.1.dist-info/RECORD
